ch55xtool/__init__.py
ch55xtool/__main__.py
ch55xtool/ch55xtool.py
ch55xtool/extended.wcfg
ch55xtool/typeall.wcfg
ch55xtool-1.0.4.dist-info/LICENSE
ch55xtool-1.0.4.dist-info/METADATA
ch55xtool-1.0.4.dist-info/WHEEL
ch55xtool-1.0.4.dist-info/entry_points.txt
ch55xtool-1.0.4.dist-info/top_level.txt
ch55xtool-1.0.4.dist-info/RECORD
