Metadata-Version: 2.1
Name: ch55xtool
Version: 1.0.4
Summary: An open sourced python tool for flashing WCH CH55x series USB microcontroller
Home-page: https://github.com/MarsTechHAN/ch552tool
Author: Han Xiao
Author-email: hansh-sz@hotmail.com
Maintainer: https://github.com/MarsTechHAN/ch552tool/graphs/contributors
Maintainer-email: hansh-sz@hotmail.com
License: UNKNOWN
Platform: all
Classifier: Development Status :: 4 - Beta
Classifier: Operating System :: OS Independent
Classifier: Intended Audience :: Developers
Classifier: License :: OSI Approved :: MIT License
Classifier: Environment :: Console
Classifier: Natural Language :: English
Classifier: Programming Language :: Python
Classifier: Programming Language :: Python :: Implementation
Classifier: Programming Language :: Python :: 2.7
Classifier: Programming Language :: Python :: 3
Classifier: Programming Language :: Python :: 3.6
Classifier: Programming Language :: Python :: 3.7
Classifier: Programming Language :: Python :: 3.8
Classifier: Programming Language :: Python :: 3.9
Classifier: Programming Language :: Python :: 3.10
Classifier: Programming Language :: Python :: 3.11
Classifier: Topic :: Software Development :: Embedded Systems
Requires-Python: >=3.5
License-File: LICENSE
Requires-Dist: pyusb (>=1.0.0)
